dv_flow/mgr/__init__.py
dv_flow/mgr/__main__.py
dv_flow/mgr/cache_config.py
dv_flow/mgr/cache_lock.py
dv_flow/mgr/cache_provider.py
dv_flow/mgr/cache_provider_dir.py
dv_flow/mgr/cache_util.py
dv_flow/mgr/cond_def.py
dv_flow/mgr/config.py
dv_flow/mgr/config_def.py
dv_flow/mgr/data_callable.py
dv_flow/mgr/dfm_server.py
dv_flow/mgr/dynamic_scheduler.py
dv_flow/mgr/eval_jq.py
dv_flow/mgr/exec_callable.py
dv_flow/mgr/exec_gen_callable.py
dv_flow/mgr/expr_eval.py
dv_flow/mgr/expr_parser.py
dv_flow/mgr/ext_rgy.py
dv_flow/mgr/extend_def.py
dv_flow/mgr/fileset.py
dv_flow/mgr/fragment_def.py
dv_flow/mgr/hash_provider.py
dv_flow/mgr/hash_provider_default.py
dv_flow/mgr/hash_provider_sv.py
dv_flow/mgr/listener_list.py
dv_flow/mgr/loader_scope.py
dv_flow/mgr/marker_listener.py
dv_flow/mgr/name_resolution.py
dv_flow/mgr/need_def.py
dv_flow/mgr/null_callable.py
dv_flow/mgr/out
dv_flow/mgr/package.py
dv_flow/mgr/package_def.py
dv_flow/mgr/package_factory.py
dv_flow/mgr/package_import_spec.py
dv_flow/mgr/package_loader.py
dv_flow/mgr/package_loader_p.py
dv_flow/mgr/package_node.py
dv_flow/mgr/package_provider.py
dv_flow/mgr/package_provider_toml.py
dv_flow/mgr/package_provider_yaml.py
dv_flow/mgr/package_scope.py
dv_flow/mgr/param.py
dv_flow/mgr/param_builder.py
dv_flow/mgr/param_def.py
dv_flow/mgr/param_def_collection.py
dv_flow/mgr/param_ref_eval.py
dv_flow/mgr/parser.out
dv_flow/mgr/parsetab.py
dv_flow/mgr/pypkg.py
dv_flow/mgr/pytask.py
dv_flow/mgr/pytask_callable.py
dv_flow/mgr/root_package.py
dv_flow/mgr/shell_callable.py
dv_flow/mgr/srcinfo.py
dv_flow/mgr/symbol_scope.py
dv_flow/mgr/task.py
dv_flow/mgr/task_data.py
dv_flow/mgr/task_def.py
dv_flow/mgr/task_gen_ctxt.py
dv_flow/mgr/task_graph_builder.py
dv_flow/mgr/task_graph_dot_writer.py
dv_flow/mgr/task_listener_log.py
dv_flow/mgr/task_listener_progress.py
dv_flow/mgr/task_listener_progress_bar.py
dv_flow/mgr/task_listener_trace.py
dv_flow/mgr/task_listener_tui.py
dv_flow/mgr/task_node.py
dv_flow/mgr/task_node_compound.py
dv_flow_mgr-1.12.21548373127.dist-info/licenses/LICENSE
dv_flow_mgr-1.12.21548373127.dist-info/METADATA
dv_flow_mgr-1.12.21548373127.dist-info/WHEEL
dv_flow_mgr-1.12.21548373127.dist-info/entry_points.txt
dv_flow_mgr-1.12.21548373127.dist-info/top_level.txt
dv_flow_mgr-1.12.21548373127.dist-info/RECORD
