Metadata-Version: 2.4
Name: dv-flow-mgr
Version: 1.12.21548373127
Summary: DV Flow Manager - Data-driven, parameterizable workflow orchestration
Author-email: Matthew Ballance <matt.ballance@gmail.com>
License:                                  Apache License
License-File: LICENSE
Requires-Dist: jq
Requires-Dist: pydantic
Requires-Dist: pyyaml
Requires-Dist: rich
Requires-Dist: tomli
Requires-Dist: toposort
Requires-Dist: svdep
Dynamic: license-file
